README.md
setup.py
fundsr/__init__.py
fundsr/fundsr.py
fundsr/holiday.py
fundsr.egg-info/PKG-INFO
fundsr.egg-info/SOURCES.txt
fundsr.egg-info/dependency_links.txt
fundsr.egg-info/top_level.txt