Metadata-Version: 2.1
Name: fundsr
Version: 1.0.0
Summary: UNKNOWN
Home-page: https://github.com/YEZIHANGISM/fundsr
Author: yezihangism
Author-email: yezihangism@gmail.com
License: UNKNOWN
Platform: UNKNOWN
